{"offset": 0, "limit": 100, "count": 5, "history": [
    {
        "start_time": 1405959312,
        "request_time": 1405958985,
        "distance": 3.1,
        "product_id": 1,
        "end_time": 1405959612,
        "uuid": 1,
        "status": "completed"
    },
    {
        "start_time": 1406611209,
        "request_time": 1406610912,
        "distance": 2.8,
        "product_id": 2,
        "end_time": 1406611509,
        "uuid": 1,
        "status": "completed"
    },
    {
        "start_time": 1407920287,
        "request_time": 1407919502,
        "distance": 3.2,
        "product_id": 3,
        "end_time": 1407921297,
        "uuid": 1,
        "status": "completed"
    },
    {
        "start_time": 1408540623,
        "request_time": 1408540443,
        "distance": 4.1,
        "product_id": 4,
        "end_time": 1408541583,
        "uuid": 1,
        "status": "completed"
    },
    {
        "start_time": 1411381562,
        "request_time": 1411381200,
        "distance": 9.8,
        "product_id": 5,
        "end_time": 1411382485,
        "uuid": 1,
        "status": "completed"
    }
]}
